brynq_sdk_loket/__init__.py
brynq_sdk_loket/absence_progress.py
brynq_sdk_loket/absences.py
brynq_sdk_loket/administrations.py
brynq_sdk_loket/benefit_inkind_types.py
brynq_sdk_loket/benefits_and_deductions.py
brynq_sdk_loket/benefits_inkind.py
brynq_sdk_loket/children.py
brynq_sdk_loket/contacts.py
brynq_sdk_loket/custom_fields.py
brynq_sdk_loket/declarations.py
brynq_sdk_loket/departments.py
brynq_sdk_loket/employee_custom_fields.py
brynq_sdk_loket/employees.py
brynq_sdk_loket/employers.py
brynq_sdk_loket/employment_custom_fields.py
brynq_sdk_loket/employments.py
brynq_sdk_loket/functions.py
brynq_sdk_loket/leave.py
brynq_sdk_loket/leave_balance.py
brynq_sdk_loket/leave_request.py
brynq_sdk_loket/leave_types.py
brynq_sdk_loket/loket.py
brynq_sdk_loket/organizational_entities.py
brynq_sdk_loket/partners.py
brynq_sdk_loket/payslips.py
brynq_sdk_loket/pension_benefits.py
brynq_sdk_loket/providers.py
brynq_sdk_loket/social_security_benefits.py
brynq_sdk_loket/utils.py
brynq_sdk_loket/work_related_costs_scheme_financials.py
brynq_sdk_loket/working_hours.py
brynq_sdk_loket/year_end_statements.py
brynq_sdk_loket/schemas/__init__.py
brynq_sdk_loket/schemas/absence_progress.py
brynq_sdk_loket/schemas/absences.py
brynq_sdk_loket/schemas/administrations.py
brynq_sdk_loket/schemas/base.py
brynq_sdk_loket/schemas/benefit_inkind_types.py
brynq_sdk_loket/schemas/benefits_and_deductions.py
brynq_sdk_loket/schemas/benefits_inkind.py
brynq_sdk_loket/schemas/children.py
brynq_sdk_loket/schemas/contacts.py
brynq_sdk_loket/schemas/custom_fields.py
brynq_sdk_loket/schemas/declarations.py
brynq_sdk_loket/schemas/departments.py
brynq_sdk_loket/schemas/employee_custom_fields.py
brynq_sdk_loket/schemas/employees.py
brynq_sdk_loket/schemas/employers.py
brynq_sdk_loket/schemas/employment_custom_fields.py
brynq_sdk_loket/schemas/employments.py
brynq_sdk_loket/schemas/functions.py
brynq_sdk_loket/schemas/leave.py
brynq_sdk_loket/schemas/leave_balance.py
brynq_sdk_loket-1.0.1.dist-info/METADATA
brynq_sdk_loket-1.0.1.dist-info/WHEEL
brynq_sdk_loket-1.0.1.dist-info/top_level.txt
brynq_sdk_loket-1.0.1.dist-info/RECORD
