Metadata-Version: 2.4
Name: brynq_sdk_loket
Version: 1.0.1
Summary: BrynQ SDK for Loket integration
Author: BrynQ
Author-email: support@brynq.com
License: BrynQ License
Requires-Dist: brynq-sdk-brynq<5,>=4
Requires-Dist: brynq-sdk-functions>=2
Requires-Dist: requests<=3,>=2
Dynamic: author
Dynamic: author-email
Dynamic: description
Dynamic: license
Dynamic: requires-dist
Dynamic: summary
